## 源码

```java
package com.ylsh.jvm.bytecode;

public class Sty001 {
    private int a = 1;
    public int getA(){
        return a;
    }
    public void setA(int a){
        this.a = a;
    }
}
```

## //通过javap命令查看类的具体信息

 javap -v classes/com/ylsh/jvm/bytecode/Sty001.class 

Classfile /Users/yexiaoheiheliunuannuan/IdeaProjects/ylsh-study/target/classes/com/ylsh/jvm/bytecode/Sty001.class

 Last modified 2019-12-26; size 486 bytes

 MD5 checksum c2402c97998d4f3ddee11ff3b6c10638

 Compiled from "Sty001.java"

public class com.ylsh.jvm.bytecode.Sty001

 minor version: 0

 major version: 52

 flags: ACC_PUBLIC, ACC_SUPER

Constant pool:

  \#1 = Methodref     #4.#20     // java/lang/Object."<init>":()V

  \#2 = Fieldref      #3.#21     // com/ylsh/jvm/bytecode/Sty001.a:I

  \#3 = Class       #22      // com/ylsh/jvm/bytecode/Sty001

  \#4 = Class       #23      // java/lang/Object

  \#5 = Utf8        a

  \#6 = Utf8        I  //

  \#7 = Utf8        <init>

  \#8 = Utf8        ()V

  \#9 = Utf8        Code

 \#10 = Utf8        LineNumberTable

 \#11 = Utf8        LocalVariableTable

 \#12 = Utf8        this

 \#13 = Utf8        Lcom/ylsh/jvm/bytecode/Sty001;

 \#14 = Utf8        getA

 \#15 = Utf8        ()I  //无参方法，返回int值

 \#16 = Utf8        setA

 \#17 = Utf8        (I)V

 \#18 = Utf8        SourceFile

 \#19 = Utf8        Sty001.java

 \#20 = NameAndType    #7:#8     // "<init>":()V

 \#21 = NameAndType    #5:#6     // a:I

 \#22 = Utf8        com/ylsh/jvm/bytecode/Sty001

 \#23 = Utf8        java/lang/Object

{

 public com.ylsh.jvm.bytecode.Sty001();

  descriptor: ()V

  flags: ACC_PUBLIC

  Code:

   stack=2, locals=1, args_size=1

​     0: aload_0

​     1: invokespecial #1         // Method java/lang/Object."<init>":()V

​     4: aload_0

​     5: iconst_1

​     6: putfield   #2         // Field a:I

​     9: return

   LineNumberTable:

​    line 3: 0

​    line 5: 4

   LocalVariableTable:

​    Start Length Slot Name  Signature

​      0   10   0 this  Lcom/ylsh/jvm/bytecode/Sty001;



 public int getA();

  descriptor: ()I

  flags: ACC_PUBLIC

  Code:

   stack=1, locals=1, args_size=1

​     0: aload_0

​     1: getfield   #2         // Field a:I

​     4: ireturn

   LineNumberTable:

​    line 8: 0

   LocalVariableTable:

​    Start Length Slot Name  Signature

​      0    5   0 this  Lcom/ylsh/jvm/bytecode/Sty001;



 public void setA(int);

  descriptor: (I)V

  flags: ACC_PUBLIC

  Code:

   stack=2, locals=2, args_size=2

​     0: aload_0

​     1: iload_1

​     2: putfield   #2         // Field a:I

​     5: return

   LineNumberTable:

​    line 12: 0

​    line 13: 5

   LocalVariableTable:

​    Start Length Slot Name  Signature

​      0    6   0 this  Lcom/ylsh/jvm/bytecode/Sty001;

​      0    6   1   a  I

}

SourceFile: "Sty001.java"



## 通过Hex Fiend查看Sty001.class文件

| Sty001.class内的16进制数据                                   | 对应的字符 |
| ------------------------------------------------------------ | ---------- |
| CA FE BA BE 00 00 00 34 00 18 0A 00 04 00 14 09 00 03 00 15 07 00 16 07 00 17 01 00 01 61 01 00 01 49 01 00 06 3C 69 6E 69 74 3E 01 00 03 28 29 56 01 00 04 43 6F 64 65 01 00 0F 4C 69 6E 65 4E 75 6D 62 65 72 54 61 62 6C 65 01 00 12 4C 6F 63 61 6C 56 61 72 69 61 62 6C 65 54 61 62 6C 65 01 00 04 74 68 69 73 01 00 1E 4C 63 6F 6D 2F 79 6C 73 68 2F 6A 76 6D 2F 62 79 74 65 63 6F 64 65 2F 53 74 79 30 30 31 3B 01 00 04 67 65 74 41 01 00 03 28 29 49 01 00 04 73 65 74 41 01 00 04 28 49 29 56 01 00 0A 53 6F 75 72 63 65 46 69 6C 65 01 00 0B 53 74 79 30 30 31 2E 6A 61 76 61 0C 00 07 00 08 0C 00 05 00 06 01 00 1C 63 6F 6D 2F 79 6C 73 68 2F 6A 76 6D 2F 62 79 74 65 63 6F 64 65 2F 53 74 79 30 30 31 01 00 10 6A 61 76 61 2F 6C 61 6E 67 2F 4F 62 6A 65 63 74 00 21 00 03 00 04 00 00 00 01 00 02 00 05 00 06 00 00 00 03 00 01 00 07 00 08 00 01 00 09 00 00 00 38 00 02 00 01 00 00 00 0A 2A B7 00 01 2A 04 B5 00 02 B1 00 00 00 02 00 0A 00 00 00 0A 00 02 00 00 00 03 00 04 00 05 00 0B 00 00 00 0C 00 01 00 00 00 0A 00 0C 00 0D 00 00 00 01 00 0E 00 0F 00 01 00 09 00 00 00 2F 00 01 00 01 00 00 00 05 2A B4 00 02 AC 00 00 00 02 00 0A 00 00 00 06 00 01 00 00 00 08 00 0B 00 00 00 0C 00 01 00 00 00 05 00 0C 00 0D 00 00 00 01 00 10 00 11 00 01 00 09 00 00 00 3E 00 02 00 02 00 00 00 06 2A 1B B5 00 02 B1 00 00 00 02 00 0A 00 00 00 0A 00 02 00 00 00 0C 00 05 00 0D 00 0B 00 00 00 16 00 02 00 00 00 06 00 0C 00 0D 00 00 00 00 00 06 00 05 00 06 00 01 00 01 00 12 00 00 00 02 00 13 |            |



### 分析

##### 魔数

4个字节的魔数CA FE BA BE

##### 主次版本

紧接着是次 主版本号，各两个字节 00 00 00 34 

​	次版本号00 00为0；主版本号00 34为52表示jdk1.8

##### 常量池信息

查看16进制对应的字符串，可去此网站进行查看http://www.ab126.com/goju/1711.html 

这里需要对16进制转换为10进制，以下 =左边是16进制，右边是10进制

00 18 =24，常量池的长度为24，0默认是null，不展示，所以上面javap 反编译展示出来的常量池中的数据有23个。

0A=10表示constant_methodref_info

00 04=4 表示指向 \#4 = Class       #23      // java/lang/Object

00 14=20表示指向 \#20 = NameAndType    #7:#8     // "<init>":()V

09=9表示constant_fieldref_info

 00 03=3指向\#3 = Class       #22      // com/ylsh/jvm/bytecode/Sty001

 00 15=21指向 \#21 = NameAndType    #5:#6     // a:I

 07=7 表示constant_class_info

 00 16=21 指向 \#21 = NameAndType    #5:#6     // a:I

 07=7 表示constant_class_info

 00 17=23 指向\#23 = Utf8        java/lang/Object

 01=1 表示constant_urf8_info

 00 01 =1 1个字节长度

61 对应的accii是a

01= 1 表示constant_urf8_info

 00 01=1 1个字节长度

 49 对应的accii是I

 01 =1 表示constant_urf8_info

00 06 =6 个字节长度

3C 69 6E 69 74 3E 对应asccii 是< i n i t > 

01 =1 表示constant_urf8_info

00 03 =3 3个字节长度

28 29 56 对应asccii是 ( ) V 

01 =1表示constant_urf8_info

00 04 =4 4个字节长度

43 6F 64 65 对应ascii是C o d e

 01=1表示constant_urf8_info

 00 0F=15 15个字节长度

 4C 69 6E 65 4E 75 6D 62 65 72 54 61 62 6C 65  accii是 L i n e N u m b e r T a b l e 

01=1

 00 12=18

 4C 6F 63 61 6C 56 61 72 69 61 62 6C 65 54 61 62 6C 65

 01 =1

00 04=4

 74 68 69 73

 01=1

 00 1E=30

 4C 63 6F 6D 2F 79 6C 73 68 2F 6A 76 6D 2F 62 79 74 65 63 6F 64 65 2F 53 74 79 30 30 31 3B 

01=1

 00 04=4

 67 65 74 41

 01=1

 00 03 =3

28 29 49

 01=1

 00 04=4

 73 65 74 41 

01=1

 00 04 =4

28 49 29 56 

01 =1

00 0A =10

53 6F 75 72 63 65 46 69 6C 65

 01=1

 00 0B =11

53 74 79 30 30 31 2E 6A 61 76 61 

0C=12 表示constant_nameandtype_info 

 00 07 =7 指向索引#7

00 08 =8 指向索引#8

0C =12

00 05 指向索引#5

00 06 指向缩影#6

 01=1 

00 1C =28

63 6F 6D 2F 79 6C 73 68 2F 6A 76 6D 2F 62 79 74 65 63 6F 64 65 2F 53 74 79 30 30 31 

01 =1

00 10 =16

6A 61 76 61 2F 6C 61 6E 67 2F 4F 62 6A 65 63 74  对应ascii是j a v a / l a n g / O b j e c t 

##### 访问标示 2个字节

00 21 

00 03 00 04 00 00 00 01 00 02 00 05 00 06 00 00 00 03 00 01 00 07 00 08 00 01 00 09 00 00 00 38 00 02 00 01 00 00 00 0A 2A B7 00 01 2A 04 B5 00 02 B1 00 00 00 02 00 0A 00 00 00 0A 00 02 00 00 00 03 00 04 00 05 00 0B 00 00 00 0C 00 01 00 00 00 0A 00 0C 00 0D 00 00 00 01 00 0E 00 0F 00 01 00 09 00 00 00 2F 00 01 00 01 00 00 00 05 2A B4 00 02 AC 00 00 00 02 00 0A 00 00 00 06 00 01 00 00 00 08 00 0B 00 00 00 0C 00 01 00 00 00 05 00 0C 00 0D 00 00 00 01 00 10 00 11 00 01 00 09 00 00 00 3E 00 02 00 02 00 00 00 06 2A 1B B5 00 02 B1 00 00 00 02 00 0A 00 00 00 0A 00 02 00 00 00 0C 00 05 00 0D 00 0B 00 00 00 16 00 02 00 00 00 06 00 0C 00 0D 00 00 00 00 00 06 00 05 00 06 00 01 00 01 00 12 00 00 00 02 00 13