```java
public class Sty002 {
    String str = "hello world";
    private int x =5;
    public static Integer in = 10;
    public Sty002(){
    }
    public Sty002(int i){
        System.out.println("abc");
    }
    public static void main(String[] args){
        Sty002 sty002 = new Sty002();
    }
    private synchronized void setX(int x){
        this.x = x;
    }
    private void test(String str){
        synchronized (str){
            System.out.println("hello wordl");
        }
    }
    private synchronized static void test2(){

    }
}
```

 javap -v -p com.ylsh.jvm.bytecode.Sty002//通过此命令查看Sty002.class的详细信息

Classfile /Users/yexiaoheiheliunuannuan/IdeaProjects/ylsh-study/target/classes/com/ylsh/jvm/bytecode/Sty002.class

 Last modified 2019-12-30; size 1350 bytes

 MD5 checksum cad74dd77d14343d2fb93c716842e433

 Compiled from "Sty002.java"

public class com.ylsh.jvm.bytecode.Sty002

 minor version: 0

 major version: 52

 flags: ACC_PUBLIC, ACC_SUPER

Constant pool:

  \#1 = Methodref     #13.#46    // java/lang/Object."<init>":()V

  \#2 = String       #47      // hello world

  \#3 = Fieldref      #8.#48     // com/ylsh/jvm/bytecode/Sty002.str:Ljava/lang/String;

  \#4 = Fieldref      #8.#49     // com/ylsh/jvm/bytecode/Sty002.x:I

  \#5 = Fieldref      #50.#51    // java/lang/System.out:Ljava/io/PrintStream;

  \#6 = String       #52      // abc

  \#7 = Methodref     #53.#54    // java/io/PrintStream.println:(Ljava/lang/String;)V

  \#8 = Class       #55      // com/ylsh/jvm/bytecode/Sty002

  \#9 = Methodref     #8.#46     // com/ylsh/jvm/bytecode/Sty002."<init>":()V

 \#10 = String       #56      // hello wordl

 \#11 = Methodref     #57.#58    // java/lang/Integer.valueOf:(I)Ljava/lang/Integer;

 \#12 = Fieldref      #8.#59     // com/ylsh/jvm/bytecode/Sty002.in:Ljava/lang/Integer;

 \#13 = Class       #60      // java/lang/Object

 \#14 = Utf8        str

 \#15 = Utf8        Ljava/lang/String;

 \#16 = Utf8        x

 \#17 = Utf8        I

 \#18 = Utf8        in

 \#19 = Utf8        Ljava/lang/Integer;

 \#20 = Utf8        <init>

 \#21 = Utf8        ()V

 \#22 = Utf8        Code

 \#23 = Utf8        LineNumberTable

 \#24 = Utf8        LocalVariableTable

 \#25 = Utf8        this

 \#26 = Utf8        Lcom/ylsh/jvm/bytecode/Sty002;

 \#27 = Utf8        (I)V

 \#28 = Utf8        i

 \#29 = Utf8        main

 \#30 = Utf8        ([Ljava/lang/String;)V

 \#31 = Utf8        args

 \#32 = Utf8        [Ljava/lang/String;

 \#33 = Utf8        sty002

 \#34 = Utf8        setX

 \#35 = Utf8        test

 \#36 = Utf8        (Ljava/lang/String;)V

 \#37 = Utf8        StackMapTable

 \#38 = Class       #55      // com/ylsh/jvm/bytecode/Sty002

 \#39 = Class       #61      // java/lang/String

 \#40 = Class       #60      // java/lang/Object

 \#41 = Class       #62      // java/lang/Throwable

 \#42 = Utf8        test2

 \#43 = Utf8        <clinit>

 \#44 = Utf8        SourceFile

 \#45 = Utf8        Sty002.java

 \#46 = NameAndType    #20:#21    // "<init>":()V

 \#47 = Utf8        hello world

 \#48 = NameAndType    #14:#15    // str:Ljava/lang/String;

 \#49 = NameAndType    #16:#17    // x:I

 \#50 = Class       #63      // java/lang/System

 \#51 = NameAndType    #64:#65    // out:Ljava/io/PrintStream;

 \#52 = Utf8        abc

 \#53 = Class       #66      // java/io/PrintStream

 \#54 = NameAndType    #67:#36    // println:(Ljava/lang/String;)V

 \#55 = Utf8        com/ylsh/jvm/bytecode/Sty002

 \#56 = Utf8        hello wordl

 \#57 = Class       #68      // java/lang/Integer

 \#58 = NameAndType    #69:#70    // valueOf:(I)Ljava/lang/Integer;

 \#59 = NameAndType    #18:#19    // in:Ljava/lang/Integer;

 \#60 = Utf8        java/lang/Object

 \#61 = Utf8        java/lang/String

 \#62 = Utf8        java/lang/Throwable

 \#63 = Utf8        java/lang/System

 \#64 = Utf8        out

 \#65 = Utf8        Ljava/io/PrintStream;

 \#66 = Utf8        java/io/PrintStream

 \#67 = Utf8        println

 \#68 = Utf8        java/lang/Integer

 \#69 = Utf8        valueOf

 \#70 = Utf8        (I)Ljava/lang/Integer;

{

 java.lang.String str;

  descriptor: Ljava/lang/String;

  flags:



 private int x;

  descriptor: I

  flags: ACC_PRIVATE



 public static java.lang.Integer in;

  descriptor: Ljava/lang/Integer;

  flags: ACC_PUBLIC, ACC_STATIC



 public com.ylsh.jvm.bytecode.Sty002();

  descriptor: ()V

  flags: ACC_PUBLIC

  Code:

   stack=2, locals=1, args_size=1

​     0: aload_0

​     1: invokespecial #1         // Method java/lang/Object."<init>":()V

​     4: aload_0

​     5: ldc      #2         // String hello world

​     7: putfield   #3         // Field str:Ljava/lang/String;

​    10: aload_0

​    11: iconst_5

​    12: putfield   #4         // Field x:I

​    15: return

   LineNumberTable:

​    line 12: 0

​    line 6: 4

​    line 8: 10

​    line 14: 15

   LocalVariableTable:

​    Start Length Slot Name  Signature

​      0   16   0 this  Lcom/ylsh/jvm/bytecode/Sty002;



 public com.ylsh.jvm.bytecode.Sty002(int);

  descriptor: (I)V

  flags: ACC_PUBLIC

  Code:

   stack=2, locals=2, args_size=2

​     0: aload_0

​     1: invokespecial #1         // Method java/lang/Object."<init>":()V

​     4: aload_0

​     5: ldc      #2         // String hello world

​     7: putfield   #3         // Field str:Ljava/lang/String;

​    10: aload_0

​    11: iconst_5

​    12: putfield   #4         // Field x:I

​    15: getstatic   #5         // Field java/lang/System.out:Ljava/io/PrintStream;

​    18: ldc      #6         // String abc

​    20: invokevirtual #7         // Method java/io/PrintStream.println:(Ljava/lang/String;)V

​    23: return

   LineNumberTable:

​    line 16: 0

​    line 6: 4

​    line 8: 10

​    line 17: 15

​    line 18: 23

   LocalVariableTable:

​    Start Length Slot Name  Signature

​      0   24   0 this  Lcom/ylsh/jvm/bytecode/Sty002;

​      0   24   1   i  I



 public static void main(java.lang.String[]);

  descriptor: ([Ljava/lang/String;)V

  flags: ACC_PUBLIC, ACC_STATIC

  Code:

   stack=2, locals=2, args_size=1

​     0: new      #8         // class com/ylsh/jvm/bytecode/Sty002

​     3: dup

​     4: invokespecial #9         // Method "<init>":()V

​     7: astore_1

​     8: return

   LineNumberTable:

​    line 22: 0

​    line 24: 8

   LocalVariableTable:

​    Start Length Slot Name  Signature

​      0    9   0 args  [Ljava/lang/String;

​      8    1   1 sty002  Lcom/ylsh/jvm/bytecode/Sty002;



 private synchronized void setX(int);

  descriptor: (I)V

  flags: ACC_PRIVATE, ACC_SYNCHRONIZED

  Code:

   stack=2, locals=2, args_size=2

​     0: aload_0

​     1: iload_1

​     2: putfield   #4         // Field x:I

​     5: return

   LineNumberTable:

​    line 27: 0

​    line 29: 5

   LocalVariableTable:

​    Start Length Slot Name  Signature

​      0    6   0 this  Lcom/ylsh/jvm/bytecode/Sty002;

​      0    6   1   x  I



 private void test(java.lang.String);

  descriptor: (Ljava/lang/String;)V

  flags: ACC_PRIVATE

  Code:

   stack=2, locals=4, args_size=2

​     0: aload_1

​     1: dup

​     2: astore_2

​     3: monitorenter

​     4: getstatic   #5         // Field java/lang/System.out:Ljava/io/PrintStream;

​     7: ldc      #10         // String hello wordl

​     9: invokevirtual #7         // Method java/io/PrintStream.println:(Ljava/lang/String;)V

​    12: aload_2

​    13: monitorexit

​    14: goto     22

​    17: astore_3

​    18: aload_2

​    19: monitorexit

​    20: aload_3

​    21: athrow

​    22: return

   Exception table:

​     from  to target type

​       4  14  17  any

​      17  20  17  any

   LineNumberTable:

​    line 32: 0

​    line 33: 4

​    line 34: 12

​    line 35: 22

   LocalVariableTable:

​    Start Length Slot Name  Signature

​      0   23   0 this  Lcom/ylsh/jvm/bytecode/Sty002;

​      0   23   1  str  Ljava/lang/String;

   StackMapTable: number_of_entries = 2

​    frame_type = 255 /* full_frame */

​     offset_delta = 17

​     locals = [ class com/ylsh/jvm/bytecode/Sty002, class java/lang/String, class java/lang/Object ]

​     stack = [ class java/lang/Throwable ]

​    frame_type = 250 /* chop */

​     offset_delta = 4



 private static synchronized void test2();

  descriptor: ()V

  flags: ACC_PRIVATE, ACC_STATIC, ACC_SYNCHRONIZED

  Code:

   stack=0, locals=0, args_size=0

​     0: return

   LineNumberTable:

​    line 39: 0



 static {};

  descriptor: ()V

  flags: ACC_STATIC

  Code:

   stack=1, locals=0, args_size=0

​     0: bipush    10

​     2: invokestatic #11         // Method java/lang/Integer.valueOf:(I)Ljava/lang/Integer;

​     5: putstatic   #12         // Field in:Ljava/lang/Integer;

​     8: return

   LineNumberTable:

​    line 10: 0

}

SourceFile: "Sty002.java"



hex find 16进制数据查看

| 16进制数据                                                   |      |
| ------------------------------------------------------------ | ---- |
| CA FE BA BE 00 00 00 34 00 47 0A 00 0D 00 2E 08 00 2F 09 00 08 00 30 09 00 08 00 31 09 00 32 00 33 08 00 34 0A 00 35 00 36 07 00 37 0A 00 08 00 2E 08 00 38 0A 00 39 00 3A 09 00 08 00 3B 07 00 3C 01 00 03 73 74 72 01 00 12 4C 6A 61 76 61 2F 6C 61 6E 67 2F 53 74 72 69 6E 67 3B 01 00 01 78 01 00 01 49 01 00 02 69 6E 01 00 13 4C 6A 61 76 61 2F 6C 61 6E 67 2F 49 6E 74 65 67 65 72 3B 01 00 06 3C 69 6E 69 74 3E 01 00 03 28 29 56 01 00 04 43 6F 64 65 01 00 0F 4C 69 6E 65 4E 75 6D 62 65 72 54 61 62 6C 65 01 00 12 4C 6F 63 61 6C 56 61 72 69 61 62 6C 65 54 61 62 6C 65 01 00 04 74 68 69 73 01 00 1E 4C 63 6F 6D 2F 79 6C 73 68 2F 6A 76 6D 2F 62 79 74 65 63 6F 64 65 2F 53 74 79 30 30 32 3B 01 00 04 28 49 29 56 01 00 01 69 01 00 04 6D 61 69 6E 01 00 16 28 5B 4C 6A 61 76 61 2F 6C 61 6E 67 2F 53 74 72 69 6E 67 3B 29 56 01 00 04 61 72 67 73 01 00 13 5B 4C 6A 61 76 61 2F 6C 61 6E 67 2F 53 74 72 69 6E 67 3B 01 00 06 73 74 79 30 30 32 01 00 04 73 65 74 58 01 00 04 74 65 73 74 01 00 15 28 4C 6A 61 76 61 2F 6C 61 6E 67 2F 53 74 72 69 6E 67 3B 29 56 01 00 0D 53 74 61 63 6B 4D 61 70 54 61 62 6C 65 07 00 37 07 00 3D 07 00 3C 07 00 3E 01 00 05 74 65 73 74 32 01 00 08 3C 63 6C 69 6E 69 74 3E 01 00 0A 53 6F 75 72 63 65 46 69 6C 65 01 00 0B 53 74 79 30 30 32 2E 6A 61 76 61 0C 00 14 00 15 01 00 0B 68 65 6C 6C 6F 20 77 6F 72 6C 64 0C 00 0E 00 0F 0C 00 10 00 11 07 00 3F 0C 00 40 00 41 01 00 03 61 62 63 07 00 42 0C 00 43 00 24 01 00 1C 63 6F 6D 2F 79 6C 73 68 2F 6A 76 6D 2F 62 79 74 65 63 6F 64 65 2F 53 74 79 30 30 32 01 00 0B 68 65 6C 6C 6F 20 77 6F 72 64 6C 07 00 44 0C 00 45 00 46 0C 00 12 00 13 01 00 10 6A 61 76 61 2F 6C 61 6E 67 2F 4F 62 6A 65 63 74 01 00 10 6A 61 76 61 2F 6C 61 6E 67 2F 53 74 72 69 6E 67 01 00 13 6A 61 76 61 2F 6C 61 6E 67 2F 54 68 72 6F 77 61 62 6C 65 01 00 10 6A 61 76 61 2F 6C 61 6E 67 2F 53 79 73 74 65 6D 01 00 03 6F 75 74 01 00 15 4C 6A 61 76 61 2F 69 6F 2F 50 72 69 6E 74 53 74 72 65 61 6D 3B 01 00 13 6A 61 76 61 2F 69 6F 2F 50 72 69 6E 74 53 74 72 65 61 6D 01 00 07 70 72 69 6E 74 6C 6E 01 00 11 6A 61 76 61 2F 6C 61 6E 67 2F 49 6E 74 65 67 65 72 01 00 07 76 61 6C 75 65 4F 66 01 00 16 28 49 29 4C 6A 61 76 61 2F 6C 61 6E 67 2F 49 6E 74 65 67 65 72 3B 00 21 00 08 00 0D 00 00 00 03 00 00 00 0E 00 0F 00 00 00 02 00 10 00 11 00 00 00 09 00 12 00 13 00 00 00 07 00 01 00 14 00 15 00 01 00 16 00 00 00 46 00 02 00 01 00 00 00 10 2A B7 00 01 2A 12 02 B5 00 03 2A 08 B5 00 04 B1 00 00 00 02 00 17 00 00 00 12 00 04 00 00 00 0C 00 04 00 06 00 0A 00 08 00 0F 00 0E 00 18 00 00 00 0C 00 01 00 00 00 10 00 19 00 1A 00 00 00 01 00 14 00 1B 00 01 00 16 00 00 00 5C 00 02 00 02 00 00 00 18 2A B7 00 01 2A 12 02 B5 00 03 2A 08 B5 00 04 B2 00 05 12 06 B6 00 07 B1 00 00 00 02 00 17 00 00 00 16 00 05 00 00 00 10 00 04 00 06 00 0A 00 08 00 0F 00 11 00 17 00 12 00 18 00 00 00 16 00 02 00 00 00 18 00 19 00 1A 00 00 00 00 00 18 00 1C 00 11 00 01 00 09 00 1D 00 1E 00 01 00 16 00 00 00 41 00 02 00 02 00 00 00 09 BB 00 08 59 B7 00 09 4C B1 00 00 00 02 00 17 00 00 00 0A 00 02 00 00 00 16 00 08 00 18 00 18 00 00 00 16 00 02 00 00 00 09 00 1F 00 20 00 00 00 08 00 01 00 21 00 1A 00 01 00 22 00 22 00 1B 00 01 00 16 00 00 00 3E 00 02 00 02 00 00 00 06 2A 1B B5 00 04 B1 00 00 00 02 00 17 00 00 00 0A 00 02 00 00 00 1B 00 05 00 1D 00 18 00 00 00 16 00 02 00 00 00 06 00 19 00 1A 00 00 00 00 00 06 00 10 00 11 00 01 00 02 00 23 00 24 00 01 00 16 00 00 00 85 00 02 00 04 00 00 00 17 2B 59 4D C2 B2 00 05 12 0A B6 00 07 2C C3 A7 00 08 4E 2C C3 2D BF B1 00 02 00 04 00 0E 00 11 00 00 00 11 00 14 00 11 00 00 00 03 00 17 00 00 00 12 00 04 00 00 00 20 00 04 00 21 00 0C 00 22 00 16 00 23 00 18 00 00 00 16 00 02 00 00 00 17 00 19 00 1A 00 00 00 00 00 17 00 0E 00 0F 00 01 00 25 00 00 00 18 00 02 FF 00 11 00 03 07 00 26 07 00 27 07 00 28 00 01 07 00 29 FA 00 04 00 2A 00 2A 00 15 00 01 00 16 00 00 00 19 00 00 00 00 00 00 00 01 B1 00 00 00 01 00 17 00 00 00 06 00 01 00 00 00 27 00 08 00 2B 00 15 00 01 00 16 00 00 00 21 00 01 00 00 00 00 00 09 10 0A B8 00 0B B3 00 0C B1 00 00 00 01 00 17 00 00 00 06 00 01 00 00 00 0A 00 01 00 2C 00 00 00 02 00 2D |      |

